mlai/__init__.py
mlai/deepgp_tutorial.py
mlai/gp_tutorial.py
mlai/mlai.py
mlai/mountain_car.py
mlai/plot.py
mlai-0.1.22.dist-info/METADATA
mlai-0.1.22.dist-info/WHEEL
mlai-0.1.22.dist-info/RECORD
